cord/__init__.py
cord/__main__.py
cord/abc.py
cord/activity.py
cord/appinfo.py
cord/asset.py
cord/audit_logs.py
cord/backoff.py
cord/channel.py
cord/client.py
cord/colour.py
cord/components.py
cord/context_managers.py
cord/embeds.py
cord/emoji.py
cord/enums.py
cord/errors.py
cord/file.py
cord/flags.py
cord/gateway.py
cord/guild.py
cord/http.py
cord/integrations.py
cord/interactions.py
cord/invite.py
cord/iterators.py
cord/member.py
cord/mentions.py
cord/message.py
cord/mixins.py
cord/object.py
cord/oggparse.py
cord/opus.py
cord/partial_emoji.py
cord/permissions.py
cord/player.py
cord/py.typed
cord/raw_models.py
cord/reaction.py
cord/role.py
cord/shard.py
cord/stage_instance.py
cord/state.py
cord/sticker.py
cord/team.py
cord/template.py
cord/threads.py
cord/user.py
cord/utils.py
cord/voice_client.py
cord/widget.py
cord/bin/libopus-0.x64.dll
cord/bin/libopus-0.x86.dll
cord/ext/commands/__init__.py
cord/ext/commands/_types.py
cord/ext/commands/bot.py
cord/ext/commands/cog.py
cord/ext/commands/context.py
cord/ext/commands/converter.py
cord/ext/commands/cooldowns.py
cord/ext/commands/core.py
cord/ext/commands/errors.py
cord/ext/commands/flags.py
cord/ext/commands/help.py
cord/ext/commands/view.py
cord/ext/tasks/__init__.py
cord/types/__init__.py
cord/types/activity.py
cord/types/appinfo.py
cord/types/audit_log.py
cord/types/channel.py
cord/types/components.py
cord/types/embed.py
cord/types/emoji.py
cord/types/gateway.py
cord/types/guild.py
cord/types/integration.py
cord/types/interactions.py
cord/types/invite.py
cord/types/member.py
cord/types/message.py
cord/types/raw_models.py
cord/types/role.py
cord/types/snowflake.py
cord/types/sticker.py
cord/types/team.py
cord/types/template.py
cord/types/threads.py
cord/types/user.py
cord/types/voice.py
cord/types/webhook.py
cord/types/welcome_screen.py
cord/types/widget.py
cord/ui/__init__.py
cord/ui/button.py
cord/ui/item.py
cord/ui/select.py
cord/ui/view.py
cord/webhook/__init__.py
cord/webhook/async_.py
cord/webhook/sync.py
cord.py-1.27a0.dist-info/LICENSE
cord.py-1.27a0.dist-info/METADATA
cord.py-1.27a0.dist-info/WHEEL
cord.py-1.27a0.dist-info/top_level.txt
cord.py-1.27a0.dist-info/RECORD
